CUDG/__init__.py
CUDG/VRAManager/__init__.py
CUDG/VRAManager/assigner.py
CUDG/VRAManager/cleaner.py
CUDG/VRAManager/memory.py
CUDG/gpuarray/__init__.py
CUDG/gpuarray/gpuarray.py
CUDG/linalg/__init__.py
CUDG/linalg/linalg.py
CUDG/linalg/linalgcore.py
CUDG/sparse/__init__.py
CUDG/sparse/gpusparse.py
CUDG-0.0.2.dist-info/METADATA
CUDG-0.0.2.dist-info/WHEEL
CUDG-0.0.2.dist-info/top_level.txt
CUDG-0.0.2.dist-info/RECORD
