Metadata-Version: 2.1
Name: CUDG
Version: 0.0.2
Summary: CUDG is for gpuarray type for convenience
Home-page: https://github.com/Daegeun02/cudg.git
Author: Daegeun02
Author-email: redhawkdg02@gmail.com
Keywords: CUDG,by daegeun,for convenience
Classifier: Programming Language :: Python :: 3.7
Classifier: Programming Language :: Python :: 3.8
Classifier: Programming Language :: Python :: 3.9
Classifier: Programming Language :: Python :: 3.10
Requires-Python: >=3.7
